Metadata-Version: 2.1
Name: moddagudu
Version: 1.8.4
Summary: Naa First package idhi...mast undi ga?
License-File: LICENSE.md
